gachi_http/__init__.py
gachi_http-0.1.3.dist-info/METADATA
gachi_http-0.1.3.dist-info/WHEEL
gachi_http-0.1.3.dist-info/top_level.txt
gachi_http-0.1.3.dist-info/RECORD
