Metadata-Version: 2.1
Name: gachi-http
Version: 0.1.3
Summary: Add-on over aiohttp for more convenience
Home-page: https://pypi.org/project/gachi-http
Author: xazkerboy & edman
Author-email: admin@quot.pw
License: GPL3
Platform: UNKNOWN
Requires-Python: >=3.6, <4
Requires-Dist: setuptools
Requires-Dist: aiohttp (~=3.7.3)
Requires-Dist: aiohttp-socks (~=0.5.5)
